candyland/__init__.py
candyland/__main__.py
candyland/actors/__init__.py
candyland/actors/ipfs/__init__.py
candyland/actors/ipfs/agent.py
candyland/actors/manage/__init__.py
candyland/actors/manage/fs.py
candyland/actors/storj/__init__.py
candyland/actors/storj/agent.py
candyland/components/__init__.py
candyland/components/messages/__init__.py
candyland/components/messages/message.py
candyland/components/pipelines/__init__.py
candyland/components/pipelines/base.py
candyland/core/__init__.py
candyland/core/utils/__init__.py
candyland/core/utils/clock.py
candyland/core/utils/structs.py
candyland/data/__init__.py
candyland/data/models/__init__.py
candyland/data/proofs/__init__.py
candyland/data/schemas/__init__.py
candyland-0.1.5.dist-info/LICENSE
candyland-0.1.5.dist-info/WHEEL
candyland-0.1.5.dist-info/METADATA
candyland-0.1.5.dist-info/RECORD
