Metadata-Version: 2.1
Name: candyland
Version: 0.1.5
Summary: 
Author: FL03
Author-email: jo3mccain@icloud.com
Requires-Python: >=3.7,<3.11
Classifier: Programming Language :: Python :: 3
Classifier: Programming Language :: Python :: 3.7
Classifier: Programming Language :: Python :: 3.8
Classifier: Programming Language :: Python :: 3.9
Classifier: Programming Language :: Python :: 3.10
Requires-Dist: pydantic (>=1.10.2,<2.0.0)
